mc_base/__init__.py
mc_base/cli/__init__.py
mc_base/cli/cli.py
mc_base/llv/__init__.py
mc_base/llv/faceframe.py
mc_base/llv/socketconn.py
mc_base/rag/__init__.py
mc_base-0.1.1a1.dist-info/METADATA
mc_base-0.1.1a1.dist-info/WHEEL
mc_base-0.1.1a1.dist-info/entry_points.txt
mc_base-0.1.1a1.dist-info/RECORD
