Metadata-Version: 2.1
Name: mc-base
Version: 0.1.1a1
Summary: 
Author: Mind Children
Requires-Python: >=3.11,<4.0
Classifier: Programming Language :: Python :: 3
Classifier: Programming Language :: Python :: 3.11
Classifier: Programming Language :: Python :: 3.12
Requires-Dist: python-on-whales (>=0.72.0,<0.73.0)
Requires-Dist: typer (>=0.12.5,<0.13.0)
